odoo8_addon_mail_environment-8.0.0.1.0.99.dev13-py2.7-nspkg.pth
odoo8_addon_mail_environment-8.0.0.1.0.99.dev13.dist-info/METADATA
odoo8_addon_mail_environment-8.0.0.1.0.99.dev13.dist-info/RECORD
odoo8_addon_mail_environment-8.0.0.1.0.99.dev13.dist-info/WHEEL
odoo8_addon_mail_environment-8.0.0.1.0.99.dev13.dist-info/namespace_packages.txt
odoo8_addon_mail_environment-8.0.0.1.0.99.dev13.dist-info/top_level.txt
odoo_addons/mail_environment/__init__.py
odoo_addons/mail_environment/__openerp__.py
odoo_addons/mail_environment/env_mail.py
odoo_addons/mail_environment/mail_view.xml
odoo_addons/mail_environment/i18n/ca.po
odoo_addons/mail_environment/i18n/de.po
odoo_addons/mail_environment/i18n/es.po
odoo_addons/mail_environment/i18n/fr.po
odoo_addons/mail_environment/i18n/it.po
odoo_addons/mail_environment/i18n/mail_environment.pot
odoo_addons/mail_environment/i18n/pt_BR.po
odoo_addons/mail_environment/i18n/sl.po
odoo_addons/mail_environment/i18n/tr.po
odoo_addons/mail_environment/static/description/icon.png
